{
  "chains": [
    "A",
    "A:B49"
  ],
  "pdb_id": "",
  "interactor1": "A",
  "tag": "",
  "email": "",
  "notify": false,
  "sample": false,
  "interactor2": "A:B49",
  "electrostatics": null,
  "predictions": {
    "structures": [
      "3g0f"
    ],
    "electrostatics": [
      null
    ],
    "dg_score": [
      null
    ],
    "dg_elec": [
      null
    ],
    "dg": [
      -8.6806263
    ],
    "CC": [
      1906
    ],
    "NN": [
      82
    ],
    "OO": [
      59
    ],
    "XX": [
      2
    ],
    "CN": [
      851
    ],
    "CO": [
      761
    ],
    "CX": [
      171
    ],
    "NO": [
      151
    ],
    "NX": [
      43
    ],
    "OX": [
      42
    ]
  }
}