{
  "chains": [
    "A",
    "B:38O"
  ],
  "pdb_id": "",
  "interactor1": "A",
  "tag": "",
  "email": "",
  "notify": false,
  "sample": false,
  "interactor2": "B:38O",
  "electrostatics": null,
  "predictions": {
    "structures": [
      "5am6_w"
    ],
    "electrostatics": [
      -37.2761
    ],
    "dg_score": [
      122.2281994766
    ],
    "dg_elec": [
      -7.7755779362799995
    ],
    "dg": [
      -8.0625541
    ],
    "CC": [
      2089
    ],
    "NN": [
      150
    ],
    "OO": [
      36
    ],
    "XX": [
      0
    ],
    "CN": [
      1135
    ],
    "CO": [
      721
    ],
    "CX": [
      118
    ],
    "NO": [
      212
    ],
    "NX": [
      33
    ],
    "OX": [
      34
    ]
  }
}